LICENSE
README.rst
setup.cfg
setup.py
docs/changelog.rst
src/senaite/__init__.py
src/senaite.patient.egg-info/PKG-INFO
src/senaite.patient.egg-info/SOURCES.txt
src/senaite.patient.egg-info/dependency_links.txt
src/senaite.patient.egg-info/entry_points.txt
src/senaite.patient.egg-info/namespace_packages.txt
src/senaite.patient.egg-info/not-zip-safe
src/senaite.patient.egg-info/requires.txt
src/senaite.patient.egg-info/top_level.txt
src/senaite/patient/__init__.py
src/senaite/patient/api.py
src/senaite/patient/config.py
src/senaite/patient/configure.zcml
src/senaite/patient/i18n.py
src/senaite/patient/interfaces.py
src/senaite/patient/permissions.py
src/senaite/patient/permissions.zcml
src/senaite/patient/setuphandlers.py
src/senaite/patient/validators.py
src/senaite/patient/vocabularies.py
src/senaite/patient/adapters/__init__.py
src/senaite/patient/adapters/configure.zcml
src/senaite/patient/adapters/dynamicresultsrange.py
src/senaite/patient/adapters/guards.py
src/senaite/patient/adapters/impress.py
src/senaite/patient/adapters/listing.py
src/senaite/patient/adapters/widgetvisibility.py
src/senaite/patient/browser/__init__.py
src/senaite/patient/browser/configure.zcml
src/senaite/patient/browser/controlpanel.py
src/senaite/patient/browser/patientfolder.py
src/senaite/patient/browser/client/__init__.py
src/senaite/patient/browser/client/configure.zcml
src/senaite/patient/browser/client/patients.py
src/senaite/patient/browser/patient/__init__.py
src/senaite/patient/browser/patient/add2.py
src/senaite/patient/browser/patient/configure.zcml
src/senaite/patient/browser/patient/samples.py
src/senaite/patient/browser/patient/views.py
src/senaite/patient/browser/static/resources.pt
src/senaite/patient/browser/static/assets/icons/id-card-red.svg
src/senaite/patient/browser/static/assets/icons/id-card.svg
src/senaite/patient/browser/static/assets/icons/patient.svg
src/senaite/patient/browser/static/assets/icons/patientfolder.svg
src/senaite/patient/browser/static/bundles/senaite.patient-6fd7bd9.js
src/senaite/patient/browser/theme/__init__.py
src/senaite/patient/browser/theme/configure.zcml
src/senaite/patient/browser/theme/icons.py
src/senaite/patient/browser/viewlets/__init__.py
src/senaite/patient/browser/viewlets/configure.zcml
src/senaite/patient/browser/viewlets/templates/temporary_mrn_viewlet.pt
